tool/__init__.py
tools_api/__init__.py
tools_api/wtftest.py
wttest/__init__.py
wttest/wtftest.py
test_deng_ritter-1.0.7.dist-info/LICENSE
test_deng_ritter-1.0.7.dist-info/METADATA
test_deng_ritter-1.0.7.dist-info/WHEEL
test_deng_ritter-1.0.7.dist-info/top_level.txt
test_deng_ritter-1.0.7.dist-info/RECORD
