Metadata-Version: 2.1
Name: test-deng-ritter
Version: 1.0.7
Summary: just test!
Home-page: https://github.com/dengxin5408/pip_seetting.git
Author: ritter
Author-email: 771034977@qq.com
License: MIT Licence
Keywords: python_tools
Platform: UNKNOWN
